rhdl-0.2.0.post1769781378.dist-info/licenses/LICENSE
rhdlcli/__init__.py
rhdlcli/api.py
rhdlcli/cli.py
rhdlcli/compose.py
rhdlcli/downloader.py
rhdlcli/files.py
rhdlcli/fs.py
rhdlcli/main.py
rhdlcli/options.py
rhdlcli/printer.py
rhdlcli/pull_secret.py
rhdlcli/stats.py
rhdlcli/validator.py
rhdlcli/version.py
rhdl-0.2.0.post1769781378.dist-info/METADATA
rhdl-0.2.0.post1769781378.dist-info/WHEEL
rhdl-0.2.0.post1769781378.dist-info/entry_points.txt
rhdl-0.2.0.post1769781378.dist-info/top_level.txt
rhdl-0.2.0.post1769781378.dist-info/RECORD
